{"cameraMode":{"drawMode":0,"name":"Shaded","section":"Shading Mode"},"sceneLighting":true,"audioPlay":false,"sceneViewState":{"showFog":true,"showMaterialUpdate":false,"showSkybox":true,"showFlares":true,"showImageEffects":true,"showParticleSystems":true},"in2DMode":false,"pivot":{"x":-6.88317346572876,"y":-17.81925392150879,"z":-2.5081288814544679},"rotation":{"x":-0.07150759547948837,"y":0.2849739193916321,"z":0.021322166547179223,"w":0.9556264281272888},"size":9.08747673034668,"orthographic":false}